flyplotlib/__init__.py
flyplotlib/core.py
flyplotlib/leg.py
flyplotlib/data/fly.svg
flyplotlib/data/leg.svg
flyplotlib/data/pushing.svg
flyplotlib/tests/__init__.py
flyplotlib/tests/test_core.py
flyplotlib-0.5.1.dist-info/METADATA
flyplotlib-0.5.1.dist-info/WHEEL
flyplotlib-0.5.1.dist-info/licenses/LICENSE
flyplotlib-0.5.1.dist-info/RECORD
