Metadata-Version: 2.4
Name: flyplotlib
Version: 0.5.1
Summary: Add flies to matplotlib plots.
Author-email: tkclam <thomas.lam@epfl.ch>
License-File: LICENSE
Requires-Python: >=3.10
Requires-Dist: distinctipy>=1.3.4
Requires-Dist: matplotlib>=3
Requires-Dist: numpy>=2
Requires-Dist: pandas>=2
Requires-Dist: svgpath2mpl>=1
